kronsteen/__init__.py
kronsteen/_version.py
kronsteen/actions.py
kronsteen/client.py
kronsteen/config.py
kronsteen/exceptions.py
kronsteen/finders.py
kronsteen/launcher.py
kronsteen/logging_config.py
kronsteen/models.py
kronsteen/ocr.py
kronsteen/ocr_tesseract.py
kronsteen/py.typed
kronsteen/regions.py
kronsteen/utils.py
kronsteen/vision.py
kronsteen/window_monitor.py
kronsteen-0.2.0.dist-info/licenses/LICENSE
kronsteen-0.2.0.dist-info/METADATA
kronsteen-0.2.0.dist-info/WHEEL
kronsteen-0.2.0.dist-info/top_level.txt
kronsteen-0.2.0.dist-info/RECORD
