Metadata-Version: 2.4
Name: kronsteen
Version: 0.2.0
Summary: Vision-powered desktop automation framework with OCR text recognition using Tesseract.
Author: Roman
Author-email: Roman Klym <klymroman@protonmail.com>
Project-URL: Homepage, https://github.com/romaklym/kronsteen
Project-URL: Documentation, https://github.com/romaklym/kronsteen
Project-URL: Source, https://github.com/romaklym/kronsteen
Keywords: automation,pyautogui,ocr,desktop,testing
Classifier: Programming Language :: Python :: 3
Classifier: Programming Language :: Python :: 3.9
Classifier: Programming Language :: Python :: 3.10
Classifier: Programming Language :: Python :: 3.11
Classifier: Programming Language :: Python :: 3.12
Classifier: Operating System :: OS Independent
Classifier: License :: OSI Approved :: MIT License
Classifier: Topic :: Software Development :: Testing
Classifier: Topic :: Utilities
Requires-Python: >=3.9
License-File: LICENSE
Requires-Dist: pyautogui>=0.9.54
Requires-Dist: Pillow>=10.0.0
Requires-Dist: numpy>=1.24
Requires-Dist: typing_extensions>=4.9
Requires-Dist: opencv-python>=4.9.0
Requires-Dist: pytesseract>=0.3.10
Requires-Dist: ultralytics>=8.0.0
Requires-Dist: torch>=2.0.0
Requires-Dist: torchvision>=0.15.0
Requires-Dist: roboflow>=1.0.0
Provides-Extra: dev
Requires-Dist: pytest>=7.4; extra == "dev"
Requires-Dist: mypy>=1.7; extra == "dev"
Requires-Dist: ruff>=0.1.5; extra == "dev"
Dynamic: license-file
